{"nbr_retweet": 0, "user_id": "248497712", "url": "/postingiklan/status/645086176987213824", "text": "Batik   Madura  katun santiu IDR 90K \nCek IG: @anytime_ batik  Twit @AnytimeBatik \nPIN:7566D0D0 | http:// anytimebatik.com \u00a0 pic.twitter.com/8NNuy8EoK5", "usernameTweet": "postingiklan", "datetime": "2015-09-19 11:05:04", "is_reply": false, "is_retweet": false, "has_image": true, "images": ["https://pbs.twimg.com/media/COlFmYAUYAAP2Ar.jpg"], "ID": "645086176987213824", "nbr_reply": 0, "nbr_favorite": 0}