{"nbr_retweet": 1, "user_id": "735089885338558464", "url": "/LPJJakarta/status/1017484025429200896", "text": "Le  batik  est profond\u00e9ment li\u00e9 \u00e0 l\u2019#Indon\u00e9sie . Partez \u00e0 la d\u00e9couverte de l'archipel et de ses batiks. L'\u00eele de #Madura  >>  https:// bit.ly/2KM8KKw \u00a0 \n\n#batik  #tradition  #culture  #tissu  #batikindonesia  #sekarjagad pic.twitter.com/oLj7zioB9O", "usernameTweet": "LPJJakarta", "datetime": "2018-07-13 02:01:10", "is_reply": false, "is_retweet": false, "has_image": true, "images": ["https://pbs.twimg.com/media/Dh7UVAEX4AAgjKF.jpg"], "ID": "1017484025429200896", "nbr_reply": 0, "nbr_favorite": 1}