{"nbr_retweet": 0, "user_id": "3275105251", "url": "/semuabatik/status/663597392537743360", "text": "From:  http:// ift.tt/1Nlya71 \u00a0 \n Batik  tulis  madura  Order Wa 081215933051 Line fenydwirusmay\u2026  http:// ift.tt/1k0L57s \u00a0 pic.twitter.com/MpOtTrweZf", "usernameTweet": "semuabatik", "datetime": "2015-11-09 13:02:02", "is_reply": false, "is_retweet": false, "has_image": true, "images": ["https://pbs.twimg.com/media/CTWST8vWwAAT4iu.jpg"], "ID": "663597392537743360", "nbr_reply": 0, "nbr_favorite": 0}