{"nbr_retweet": 0, "user_id": "522182826", "url": "/PuspitaFM/status/914666540405886976", "text": "# MorningAction \nMotif  batik   madura   cenderung banyak bermain pada pola sederhana tp dibentuk rapi dan meyukai warna yang cerah  pic.twitter.com/tyMwBVfBVA", "usernameTweet": "PuspitaFM", "datetime": "2017-10-02 08:41:11", "is_reply": false, "is_retweet": false, "has_image": true, "images": ["https://pbs.twimg.com/media/DLGMXIPU8AAM2pd.jpg"], "ID": "914666540405886976", "nbr_reply": 1, "nbr_favorite": 1}