{"nbr_retweet": 0, "user_id": "840400129265868800", "url": "/tabinaco_batik/status/840499469279932416", "text": "Jual kain  batik   madura  - bahan santyu  | Tokopedia  https://www. tokopedia.com/tabinabatik9/k ain-batik-madura-bahan-santyu-10 \u00a0 \u2026  #kainbatikmadurabahansantyu  #Tokopedia  lewat @tokopedia pic.twitter.com/i3Bmsuw2ll", "usernameTweet": "tabinaco_batik", "datetime": "2017-03-11 16:47:43", "is_reply": false, "is_retweet": false, "has_image": true, "images": ["https://pbs.twimg.com/media/C6oNys7WcAASgxw.jpg"], "ID": "840499469279932416", "nbr_reply": 0, "nbr_favorite": 0}