{"nbr_retweet": 0, "user_id": "1336057916", "url": "/GHINASHOPS/status/573842099012919296", "text": "BATIK  TULIS  MADURA   kode E1  pic.twitter.com/a0GYVhN58p  | DELIVERY ALL INDONESIA | PIN:21E1AD5A - 085331155000  http://www. GhinaShop.com \u00a0", "usernameTweet": "GHINASHOPS", "datetime": "2015-03-06 20:46:32", "is_reply": false, "is_retweet": false, "has_image": true, "images": ["https://pbs.twimg.com/media/Bde255KCIAALIw7.jpg"], "ID": "573842099012919296", "nbr_reply": 0, "nbr_favorite": 0}