{"nbr_retweet": 0, "user_id": "2469583392", "url": "/rhartono01/status/517499477507063809", "text": "1. Motif La' Ola'  batik  Tanjungbumi Bangkalan  Madura  yg d Pake Presiden ktika Presmian Suramadu #Hari   Batik  Nasional  pic.twitter.com/AlqAONO6th", "usernameTweet": "rhartono01", "datetime": "2014-10-02 09:21:04", "is_reply": false, "is_retweet": false, "has_image": true, "images": ["https://pbs.twimg.com/media/By6HCF9CEAAcLHu.jpg"], "ID": "517499477507063809", "nbr_reply": 0, "nbr_favorite": 0}